menza_cli/__init__.py
menza_cli/__main__.py
menza_cli/click_test.py
menza_cli/clickargs.py
menza_cli/config.py
menza_cli/config_test.py
menza_cli/di.py
menza_cli/api/__init__.py
menza_cli/api/agata_api.py
menza_cli/api/agata_api_impl.py
menza_cli/api/agata_api_mock.py
menza_cli/api/agata_api_test.py
menza_cli/api/agata_entity.py
menza_cli/api/lasta_api.py
menza_cli/api/lasta_api_impl.py
menza_cli/api/lasta_api_mock.py
menza_cli/api/lasta_api_test.py
menza_cli/api/lasta_entity.py
menza_cli/cli/__init__.py
menza_cli/cli/dish.py
menza_cli/cli/dish_test.py
menza_cli/cli/info.py
menza_cli/cli/info_test.py
menza_cli/cli/list.py
menza_cli/cli/list_test.py
menza_cli/cli/util.py
menza_cli/cli/util_test.py
menza_cli/cli/week.py
menza_cli/cli/week_test.py
menza_cli/gui/__init__.py
menza_cli/gui/dish.py
menza_cli/gui/info.py
menza_cli/gui/key_handler.py
menza_cli/gui/main.py
menza_cli/gui/menu.py
menza_cli/gui/rating.py
menza_cli/gui/week.py
menza_cli/repo/__init__.py
menza_cli/repo/repo.py
menza_cli/repo/repo_impl.py
menza_cli/repo/repo_test.py
menza_cli-0.2.0.dist-info/LICENSE
menza_cli-0.2.0.dist-info/METADATA
menza_cli-0.2.0.dist-info/WHEEL
menza_cli-0.2.0.dist-info/entry_points.txt
menza_cli-0.2.0.dist-info/top_level.txt
menza_cli-0.2.0.dist-info/RECORD
