Metadata-Version: 2.2
Name: menza_cli
Version: 0.2.0
Summary: Dish menus for CTU cafeterias - nice CLI interface
Author-email: Petr Laštovička <krasik.peta@seznam.cz>
License:                     GNU GENERAL PUBLIC LICENSE
Project-URL: Homepage, https://github.com/Lastaapps/menza-cli
Project-URL: Bug Tracker, https://github.com/Lastaapps/menza-cli/issues
Keywords: menza,cafeteria,ctu,cvut,Prague,cli
Classifier: Environment :: Console :: Curses
Classifier: Framework :: Pytest
Classifier: Intended Audience :: End Users/Desktop
Classifier: License :: OSI Approved :: GNU General Public License v3 (GPLv3)
Classifier: Natural Language :: English
Classifier: Natural Language :: Czech
Classifier: Operating System :: POSIX :: Linux
Classifier: Programming Language :: Python :: 3.10
Requires-Python: >=3.10
License-File: LICENSE
Requires-Dist: click>=8.1.3
Requires-Dist: pytest>=7.2.0
Requires-Dist: requests>=2.28.1
Requires-Dist: result>=0.9.0
